pseudorandom/__init__.py
pseudorandom/random.py
CoolRandom-0.1.dist-info/LICENSE
CoolRandom-0.1.dist-info/METADATA
CoolRandom-0.1.dist-info/WHEEL
CoolRandom-0.1.dist-info/top_level.txt
CoolRandom-0.1.dist-info/RECORD
