Metadata-Version: 2.1
Name: CoolRandom
Version: 0.1
Summary: A Python package for pseudo random numbers generation
Home-page: https://github.com/carrasquel/pseudo-random
Author: Nelson Carrasquel
Author-email: carrasquel@outlook.com
License: MIT
Platform: UNKNOWN
Classifier: Programming Language :: Python :: 3
Classifier: License :: OSI Approved :: MIT License
Classifier: Operating System :: OS Independent
